CHANGELOG.txt
MANIFEST.in
README.md
setup.py
./bin/dartui
DarTui.egg-info/PKG-INFO
DarTui.egg-info/SOURCES.txt
DarTui.egg-info/dependency_links.txt
DarTui.egg-info/requires.txt
DarTui.egg-info/top_level.txt
dartui/__init__.py
dartui/actions.py
dartui/common.py
dartui/config.py
dartui/formatters.py
dartui/http.py
dartui/pages.py
dartui/utils.py
dartui/sql/__init__.py
dartui/sql/converters.py
dartui/sql/scripts/ip2nation.defaults.gz
dartui/sql/scripts/ip2nation.struct
dartui/sql/scripts/recent_torrent_dests.struct
dartui/sql/scripts/settings.struct
dartui/sql/scripts/settings_test.struct
dartui/sql/scripts/table_versions.struct
dartui/static/css/dartui.css
dartui/static/css/jquery-ui-1.8.16.custom.css
dartui/static/css/images/ui-bg_flat_0_aaaaaa_40x100.png
dartui/static/css/images/ui-bg_flat_75_ffffff_40x100.png
dartui/static/css/images/ui-bg_glass_55_fbf9ee_1x400.png
dartui/static/css/images/ui-bg_glass_65_ffffff_1x400.png
dartui/static/css/images/ui-bg_glass_75_dadada_1x400.png
dartui/static/css/images/ui-bg_glass_75_e6e6e6_1x400.png
dartui/static/css/images/ui-bg_highlight-soft_20_2d2d2d_1x100.png
dartui/static/css/images/ui-bg_highlight-soft_30_2d2d2d_1x100.png
dartui/static/css/images/ui-bg_highlight-soft_40_1771ca_1x100.png
dartui/static/css/images/ui-bg_highlight-soft_50_1771ca_1x100.png
dartui/static/css/images/ui-bg_highlight-soft_50_34b915_1x100.png
dartui/static/css/images/ui-bg_highlight-soft_50_3ad017_1x100.png
dartui/static/css/images/ui-bg_highlight-soft_50_a3a3a3_1x100.png
dartui/static/css/images/ui-bg_highlight-soft_50_b0b0b0_1x100.png
dartui/static/css/images/ui-bg_highlight-soft_50_cacaca_1x100.png
dartui/static/css/images/ui-bg_highlight-soft_50_ea1a2d_1x100.png
dartui/static/css/images/ui-bg_inset-soft_95_fef1ec_1x100.png
dartui/static/css/images/ui-icons_222222_256x240.png
dartui/static/css/images/ui-icons_2e83ff_256x240.png
dartui/static/css/images/ui-icons_454545_256x240.png
dartui/static/css/images/ui-icons_888888_256x240.png
dartui/static/css/images/ui-icons_cd0a0a_256x240.png
dartui/static/css/images/ui-icons_ffffff_256x240.png
dartui/static/imgs/dropdown_close.png
