Metadata-Version: 1.0
Name: DarTui
Version: 1.1.0
Summary: An rTorrent web interface with a focus on simplicity, speed and responsiveness
Home-page: https://github.com/cjlucas/dartui
Author: Chris Lucas
Author-email: chris@chrisjlucas.com
License: MIT
Keywords: rtorrent p2p web ajax
Platform: UNKNOWN
Classifier: Development Status :: 5 - Production/Stable
Classifier: Intended Audience :: End Users/Desktop
Classifier: License :: OSI Approved :: MIT License
Classifier: Natural Language :: English
Classifier: Operating System :: POSIX
Classifier: Programming Language :: Python
Classifier: Topic :: Communications :: File Sharing
Classifier: Topic :: Internet :: WWW/HTTP :: WSGI :: Application
